bettyfixer/__init__.py
bettyfixer/autoprototype.py
bettyfixer/backup.py
bettyfixer/betty_fixer.py
bettyfixer/betty_handler.py
bettyfixer/errors_extractor.py
bettyfixer/extract_line.py
bettyfixer-1.4.5.2.data/scripts/install.sh
bettyfixer-1.4.5.2.dist-info/AUTHORS
bettyfixer-1.4.5.2.dist-info/METADATA
bettyfixer-1.4.5.2.dist-info/WHEEL
bettyfixer-1.4.5.2.dist-info/entry_points.txt
bettyfixer-1.4.5.2.dist-info/top_level.txt
bettyfixer-1.4.5.2.dist-info/RECORD
